mce_metrics_plugin/__init__.py
mce_metrics_plugin/session/__init__.py
mce_metrics_plugin/session/component_conflict_rate.py
mce_metrics_plugin/session/consistency.py
mce_metrics_plugin/session/context_preservation.py
mce_metrics_plugin/session/goal_success_rate.py
mce_metrics_plugin/session/groundedness.py
mce_metrics_plugin/session/information_retention.py
mce_metrics_plugin/session/intent_recognition_accuracy.py
mce_metrics_plugin/session/llm_uncertainty_scores.py
mce_metrics_plugin/session/response_completeness.py
mce_metrics_plugin/session/workflow_cohesion_index.py
mce_metrics_plugin/session/workflow_efficiency.py
mce_metrics_plugin-0.1.1.dist-info/METADATA
mce_metrics_plugin-0.1.1.dist-info/WHEEL
mce_metrics_plugin-0.1.1.dist-info/entry_points.txt
mce_metrics_plugin-0.1.1.dist-info/RECORD
