Metadata-Version: 2.4
Name: mce_metrics_plugin
Version: 0.1.1
Summary: Metrics plugin
Project-URL: Homepage, https://github.com/agntcy/telemetry-hub
Project-URL: Repository, https://github.com/agntcy/telemetry-hub
Project-URL: Issues, https://github.com/agntcy/telemetry-hub/issues
Author: AGNTCY Telemetry Hub team
License-Expression: Apache-2.0
Requires-Python: >3.8
Requires-Dist: metrics-computation-engine
Requires-Dist: pandas>=2.3.2
Requires-Dist: pydantic>=2.11.7
Provides-Extra: dev
Requires-Dist: mypy; extra == 'dev'
Requires-Dist: pytest; extra == 'dev'
Requires-Dist: pytest-cov; extra == 'dev'
Requires-Dist: ruff; extra == 'dev'
